{
  "installCommand": "csb:install",
  "buildCommand": "csb:build",
  "packages": [
    "packages/cosmjs",
    "packages/eip-1193-provider",
    "packages/encoding",
    "packages/ethers",
    "packages/http",
    "packages/sdk-browser",
    "packages/sdk-server",
    "packages/sdk-react",
    "packages/solana",
    "packages/viem",
    "packages/webauthn-stamper",
    "packages/api-key-stamper",
    "packages/wallet-stamper",
    "packages/iframe-stamper",
    "packages/crypto",
    "packages/react-native-passkey-stamper"
  ],
  "sandboxes": [],
  "node": "18"
}
